{
  "info": {
    "_postman_id": "b3132152-bf03-4835-9111-1070d2d457a7",
    "name": "Zorvyn-Finance-Server",
    "schema": "https://schema.getpostman.com/json/collection/v2.1.0/collection.json",
    "_exporter_id": "29444763"
  },
  "item": [
    {
      "name": "SignUp",
      "request": {
        "method": "POST",
        "header": [],
        "body": {
          "mode": "raw",
          "raw": "{\r\n    \"username\": \"testUser\",\r\n    \"email\": \"test@gmail.com\",\r\n    \"password\": \"test123\"\r\n}",
          "options": {
            "raw": {
              "language": "json"
            }
          }
        },
        "url": {
          "raw": "http://localhost:3000/user/signUp",
          "protocol": "http",
          "host": [
            "localhost"
          ],
          "port": "3000",
          "path": [
            "user",
            "signUp"
          ]
        }
      },
      "response": []
    },
    {
      "name": "viewer login",
      "request": {
        "method": "POST",
        "header": [],
        "body": {
          "mode": "raw",
          "raw": "{\r\n    \"email\": \"test@gmail.com\",\r\n    \"password\": \"test123\"\r\n}",
          "options": {
            "raw": {
              "language": "json"
            }
          }
        },
        "url": {
          "raw": "http://localhost:3000/user/login",
          "protocol": "http",
          "host": [
            "localhost"
          ],
          "port": "3000",
          "path": [
            "user",
            "login"
          ]
        }
      },
      "response": []
    },
    {
      "name": "analyst login",
      "request": {
        "method": "POST",
        "header": [],
        "body": {
          "mode": "raw",
          "raw": "{\r\n    \"email\": \"admin@zorvyn.in\",\r\n    \"password\": \"admin123\"\r\n}"
        },
        "url": {
          "raw": "http://localhost:3000/user/login",
          "protocol": "http",
          "host": [
            "localhost"
          ],
          "port": "3000",
          "path": [
            "user",
            "login"
          ]
        }
      },
      "response": []
    },
    {
      "name": "admin login",
      "request": {
        "method": "POST",
        "header": [],
        "body": {
          "mode": "raw",
          "raw": "{\r\n    \"email\": \"admin@zorvyn.in\",\r\n    \"password\": \"admin123\"\r\n}",
          "options": {
            "raw": {
              "language": "json"
            }
          }
        },
        "url": {
          "raw": "http://localhost:3000/user/login",
          "protocol": "http",
          "host": [
            "localhost"
          ],
          "port": "3000",
          "path": [
            "user",
            "login"
          ]
        }
      },
      "response": []
    },
    {
      "name": "logout",
      "request": {
        "method": "POST",
        "header": [],
        "body": {
          "mode": "raw",
          "raw": "{\r\n    \"email\": \"test@gmail.com\",\r\n    \"password\": \"test123\"\r\n}"
        },
        "url": {
          "raw": "http://localhost:3000/user/logout",
          "protocol": "http",
          "host": [
            "localhost"
          ],
          "port": "3000",
          "path": [
            "user",
            "logout"
          ]
        }
      },
      "response": []
    },
    {
      "name": "update role (promte or demote)",
      "request": {
        "method": "POST",
        "header": [],
        "body": {
          "mode": "raw",
          "raw": "{\r\n    \"email\": \"test@gmail.com\",\r\n    \"password\": \"test123\"\r\n}"
        },
        "url": {
          "raw": "http://localhost:3000/user/updateRole",
          "protocol": "http",
          "host": [
            "localhost"
          ],
          "port": "3000",
          "path": [
            "user",
            "updateRole"
          ]
        }
      },
      "response": []
    },
    {
      "name": "show all transactions",
      "protocolProfileBehavior": {
        "disableBodyPruning": true
      },
      "request": {
        "auth": {
          "type": "jwt",
          "jwt": [
            {
              "key": "algorithm",
              "value": "HS256",
              "type": "string"
            },
            {
              "key": "isSecretBase64Encoded",
              "value": false,
              "type": "boolean"
            },
            {
              "key": "payload",
              "value": "{}",
              "type": "string"
            },
            {
              "key": "addTokenTo",
              "value": "header",
              "type": "string"
            },
            {
              "key": "headerPrefix",
              "value": "Bearer",
              "type": "string"
            },
            {
              "key": "queryParamKey",
              "value": "token",
              "type": "string"
            },
            {
              "key": "header",
              "value": "{}",
              "type": "string"
            }
          ]
        },
        "method": "GET",
        "header": [],
        "body": {
          "mode": "raw",
          "raw": ""
        },
        "url": {
          "raw": "http://localhost:3000/transaction?page=1&limit=5",
          "protocol": "http",
          "host": [
            "localhost"
          ],
          "port": "3000",
          "path": [
            "transaction"
          ],
          "query": [
            {
              "key": "page",
              "value": "1"
            },
            {
              "key": "limit",
              "value": "5"
            }
          ]
        }
      },
      "response": []
    },
    {
      "name": "create transaction",
      "request": {
        "auth": {
          "type": "jwt",
          "jwt": [
            {
              "key": "algorithm",
              "value": "HS256",
              "type": "string"
            },
            {
              "key": "isSecretBase64Encoded",
              "value": false,
              "type": "boolean"
            },
            {
              "key": "payload",
              "value": "{}",
              "type": "string"
            },
            {
              "key": "addTokenTo",
              "value": "header",
              "type": "string"
            },
            {
              "key": "headerPrefix",
              "value": "Bearer",
              "type": "string"
            },
            {
              "key": "queryParamKey",
              "value": "token",
              "type": "string"
            },
            {
              "key": "header",
              "value": "{}",
              "type": "string"
            }
          ]
        },
        "method": "POST",
        "header": [],
        "body": {
          "mode": "raw",
          "raw": "{   \"amount\": 6000, \r\n    \"type\": \"INCOME\", \r\n    \"category\": \"Salary\",\r\n    \"date\": \"2026-04-04T11:25:56.931Z\", \r\n    \"notes\": \"Current month salary\"\r\n}",
          "options": {
            "raw": {
              "language": "json"
            }
          }
        },
        "url": {
          "raw": "http://localhost:3000/transaction/new",
          "protocol": "http",
          "host": [
            "localhost"
          ],
          "port": "3000",
          "path": [
            "transaction",
            "new"
          ]
        }
      },
      "response": []
    },
    {
      "name": "update transaction",
      "request": {
        "method": "PATCH",
        "header": [],
        "body": {
          "mode": "raw",
          "raw": "{\r\n    \"amount\": 6969\r\n}",
          "options": {
            "raw": {
              "language": "json"
            }
          }
        },
        "url": {
          "raw": "http://localhost:3000/transaction/69d0f54f3cf11a06cdd725ac",
          "protocol": "http",
          "host": [
            "localhost"
          ],
          "port": "3000",
          "path": [
            "transaction",
            "69d0f54f3cf11a06cdd725ac"
          ]
        }
      },
      "response": []
    },
    {
      "name": "delete transaction",
      "request": {
        "method": "DELETE",
        "header": [],
        "url": {
          "raw": "http://localhost:3000/transaction/69d0f54f3cf11a06cdd725ac",
          "protocol": "http",
          "host": [
            "localhost"
          ],
          "port": "3000",
          "path": [
            "transaction",
            "69d0f54f3cf11a06cdd725ac"
          ]
        }
      },
      "response": []
    },
    {
      "name": "get finanace overview",
      "request": {
        "method": "GET",
        "header": [],
        "url": {
          "raw": "http://localhost:3000/dashboard/financeOverview",
          "protocol": "http",
          "host": [
            "localhost"
          ],
          "port": "3000",
          "path": [
            "dashboard",
            "financeOverview"
          ]
        }
      },
      "response": []
    },
    {
      "name": "get catogery totals",
      "request": {
        "method": "GET",
        "header": [],
        "url": {
          "raw": "http://localhost:3000/dashboard/categoryTotals",
          "protocol": "http",
          "host": [
            "localhost"
          ],
          "port": "3000",
          "path": [
            "dashboard",
            "categoryTotals"
          ]
        }
      },
      "response": []
    },
    {
      "name": "get recent activity",
      "request": {
        "method": "GET",
        "header": [],
        "url": {
          "raw": "http://localhost:3000/dashboard/recentActivity",
          "protocol": "http",
          "host": [
            "localhost"
          ],
          "port": "3000",
          "path": [
            "dashboard",
            "recentActivity"
          ]
        }
      },
      "response": []
    },
    {
      "name": "get monthly trends",
      "request": {
        "method": "GET",
        "header": [],
        "url": {
          "raw": "http://localhost:3000/dashboard/monthlyTrends",
          "protocol": "http",
          "host": [
            "localhost"
          ],
          "port": "3000",
          "path": [
            "dashboard",
            "monthlyTrends"
          ]
        }
      },
      "response": []
    }
  ]
}